mailerlite/__init__.py
mailerlite/api_client.py
mailerlite/sdk/__init__.py
mailerlite/sdk/automations.py
mailerlite/sdk/batch.py
mailerlite/sdk/campaigns.py
mailerlite/sdk/fields.py
mailerlite/sdk/forms.py
mailerlite/sdk/groups.py
mailerlite/sdk/segments.py
mailerlite/sdk/subscribers.py
mailerlite/sdk/timezones.py
mailerlite/sdk/webhooks.py
mailerlite-0.1.10.dist-info/LICENSE
mailerlite-0.1.10.dist-info/METADATA
mailerlite-0.1.10.dist-info/WHEEL
mailerlite-0.1.10.dist-info/RECORD
